simstudio/__init__.py
simstudio_sdk-0.1.2.dist-info/METADATA
simstudio_sdk-0.1.2.dist-info/WHEEL
simstudio_sdk-0.1.2.dist-info/top_level.txt
simstudio_sdk-0.1.2.dist-info/RECORD
