Metadata-Version: 2.4
Name: simstudio-sdk
Version: 0.1.2
Summary: Sim SDK - Execute workflows programmatically
Home-page: https://github.com/simstudioai/sim
Author: Sim
Author-email: Sim <help@sim.ai>
License: Apache-2.0
Project-URL: Homepage, https://sim.ai
Project-URL: Documentation, https://docs.sim.ai
Project-URL: Repository, https://github.com/simstudioai/sim
Project-URL: Bug Reports, https://github.com/simstudioai/sim/issues
Keywords: simstudio,ai,workflow,sdk,api,automation
Classifier: Development Status :: 4 - Beta
Classifier: Intended Audience :: Developers
Classifier: License :: OSI Approved :: Apache Software License
Classifier: Operating System :: OS Independent
Classifier: Programming Language :: Python :: 3
Classifier: Programming Language :: Python :: 3.8
Classifier: Programming Language :: Python :: 3.9
Classifier: Programming Language :: Python :: 3.10
Classifier: Programming Language :: Python :: 3.11
Classifier: Programming Language :: Python :: 3.12
Classifier: Topic :: Software Development :: Libraries :: Python Modules
Classifier: Topic :: Internet :: WWW/HTTP :: HTTP Servers
Classifier: Topic :: Scientific/Engineering :: Artificial Intelligence
Requires-Python: >=3.8
Requires-Dist: requests>=2.25.0
Requires-Dist: typing-extensions>=4.0.0; python_version < "3.10"
Provides-Extra: dev
Requires-Dist: pytest>=6.0.0; extra == "dev"
Requires-Dist: pytest-asyncio>=0.18.0; extra == "dev"
Requires-Dist: black>=22.0.0; extra == "dev"
Requires-Dist: flake8>=4.0.0; extra == "dev"
Requires-Dist: mypy>=0.910; extra == "dev"
Requires-Dist: isort>=5.0.0; extra == "dev"
Requires-Dist: types-requests>=2.25.0; extra == "dev"
Dynamic: author
Dynamic: home-page
Dynamic: requires-python
